mandala/__init__.py
mandala/admin/__init__.py
mandala/admin/actions.py
mandala/admin/apps.py
mandala/admin/checks.py
mandala/admin/decorators.py
mandala/admin/exceptions.py
mandala/admin/filters.py
mandala/admin/forms.py
mandala/admin/helpers.py
mandala/admin/models.py
mandala/admin/options.py
mandala/admin/sites.py
mandala/admin/tests.py
mandala/admin/utils.py
mandala/admin/widgets.py
mandala/admin/migrations/0001_initial.py
mandala/admin/migrations/0002_logentry_remove_auto_add.py
mandala/admin/migrations/0003_logentry_add_action_flag_choices.py
mandala/admin/migrations/__init__.py
mandala/admin/templatetags/__init__.py
mandala/admin/templatetags/admin_list.py
mandala/admin/templatetags/admin_modify.py
mandala/admin/templatetags/admin_static.py
mandala/admin/templatetags/admin_urls.py
mandala/admin/templatetags/base.py
mandala/admin/templatetags/log.py
mandala/admin/views/__init__.py
mandala/admin/views/autocomplete.py
mandala/admin/views/decorators.py
mandala/admin/views/main.py
mandala/auth/__init__.py
mandala/auth/admin.py
mandala/auth/apps.py
mandala/auth/backends.py
mandala/auth/base_user.py
mandala/auth/checks.py
mandala/auth/context_processors.py
mandala/auth/decorators.py
mandala/auth/forms.py
mandala/auth/hashers.py
mandala/auth/middleware.py
mandala/auth/mixins.py
mandala/auth/models.py
mandala/auth/password_validation.py
mandala/auth/signals.py
mandala/auth/site.py
mandala/auth/tests.py
mandala/auth/tokens.py
mandala/auth/urls.py
mandala/auth/validators.py
mandala/auth/views.py
mandala/auth/migrations/0001_initial.py
mandala/auth/migrations/__init__.py
mandala-1.0.0.dist-info/LICENSE.txt
mandala-1.0.0.dist-info/METADATA
mandala-1.0.0.dist-info/WHEEL
mandala-1.0.0.dist-info/top_level.txt
mandala-1.0.0.dist-info/RECORD
