Metadata-Version: 2.1
Name: mandala
Version: 1.0.0
Summary: A RBAC auth framework for django
Home-page: https://github.com/TomTsong/mandala
Author: Tom Tsong
Author-email: congdaxia@126.com
License: UNKNOWN
Keywords: django rbac auth framework
Platform: UNKNOWN
Classifier: Development Status :: 5 - Production/Stable
Classifier: Intended Audience :: Developers
Classifier: Topic :: Software Development :: Code Generators
Classifier: License :: OSI Approved :: MIT License
Classifier: Programming Language :: Python :: 3.6
Requires-Python: >=3.6
Requires-Dist: django (>=2.2.4)
